{
    "name": "DeleteSubActionFamilies_CheckData",
    "properties": {
        "description": "",
        "folder": {
            "name": "11-AssetPortfolioActivitiesManagement/Delete"
        },
        "type": "MappingDataFlow",
        "typeProperties": {
            "sources": [
                {
                    "dataset": {
                        "referenceName": "DeleteSubActionFamilies",
                        "type": "DatasetReference"
                    },
                    "name": "ReadDeleteSubActionFamilies"
                },
                {
                    "dataset": {
                        "referenceName": "TempInput_SubActionFamiliesStatus",
                        "type": "DatasetReference"
                    },
                    "name": "SubActionFamiliesStatus"
                }
            ],
            "sinks": [
                {
                    "dataset": {
                        "referenceName": "11_310",
                        "type": "DatasetReference"
                    },
                    "name": "WriteNotExistingNameRows"
                },
                {
                    "dataset": {
                        "referenceName": "11_311",
                        "type": "DatasetReference"
                    },
                    "name": "WriteMissingNameRows"
                }
            ],
            "transformations": [
                {
                    "name": "ExistingNameInSubActionFamiliesStatus"
                },
                {
                    "name": "CheckMandatoryData"
                }
            ],
            "script": "source(output(\n\t\tName as string\n\t),\n\tallowSchemaDrift: false,\n\tvalidateSchema: true,\n\tignoreNoFilesFound: true) ~> ReadDeleteSubActionFamilies\nsource(output(\n\t\tName as string\n\t),\n\tallowSchemaDrift: false,\n\tvalidateSchema: true,\n\tignoreNoFilesFound: true) ~> SubActionFamiliesStatus\nReadDeleteSubActionFamilies, SubActionFamiliesStatus exists(ReadDeleteSubActionFamilies@Name == SubActionFamiliesStatus@Name,\n\tnegate:true,\n\tbroadcast: 'auto')~> ExistingNameInSubActionFamiliesStatus\nExistingNameInSubActionFamiliesStatus sink(allowSchemaDrift: true,\n\tvalidateSchema: false,\n\tpartitionFileNames:['11-310-NotExistingName.csv'],\n\tskipDuplicateMapInputs: true,\n\tskipDuplicateMapOutputs: true,\n\tpartitionBy('hash', 1)) ~> WriteNotExistingNameRows\nReadDeleteSubActionFamilies split(isNull(Name),\n\tdisjoint: false) ~> CheckMandatoryData@(MissingName)\nCheckMandatoryData@MissingName sink(allowSchemaDrift: true,\n\tvalidateSchema: false,\n\tpartitionFileNames:['11-311-MissColumnName.csv'],\n\tskipDuplicateMapInputs: true,\n\tskipDuplicateMapOutputs: true,\n\tpartitionBy('hash', 1)) ~> WriteMissingNameRows"
        }
    }
}